pydomywork/__init__.py
pydomywork-1.4.dist-info/LICENSE.txt
pydomywork-1.4.dist-info/METADATA
pydomywork-1.4.dist-info/WHEEL
pydomywork-1.4.dist-info/top_level.txt
pydomywork-1.4.dist-info/RECORD
