Metadata-Version: 2.1
Name: pydomywork
Version: 1.4
Summary: Do you homework with this library. This library converts computer characters to handwritten characters.
Home-page: https://github.com/Ankit404butfound//HomeworkMachine
Author: Ankit Raj Mahapatra
Author-email: ankitrajjitendra816@gmail.com
License: MIT
Download-URL: https://github.com/Ankit404butfound/HomeworkMachine/archive/1.0.tar.gz
Keywords: convert_text,img_to_handtxt,download,getimg
Platform: UNKNOWN
Classifier: Development Status :: 3 - Alpha
Classifier: Intended Audience :: Developers
Classifier: Topic :: Software Development :: Build Tools
Classifier: License :: OSI Approved :: MIT License
Classifier: Programming Language :: Python :: 3
Classifier: Programming Language :: Python :: 3.4
Classifier: Programming Language :: Python :: 3.5
Classifier: Programming Language :: Python :: 3.6
Requires-Dist: pytesseract
Requires-Dist: opencv-python
Requires-Dist: numpy
Requires-Dist: keyboard
Requires-Dist: pillow
